CHANGES.txt
LICENSE
MANIFEST.in
README.rst
setup.py
StereoVision.egg-info/PKG-INFO
StereoVision.egg-info/SOURCES.txt
StereoVision.egg-info/dependency_links.txt
StereoVision.egg-info/top_level.txt
bin/calibrate_cameras
bin/capture_chessboards
bin/images_to_pointcloud
bin/show_webcams
bin/tune_blockmatcher
doc/Makefile
doc/changes.rst
doc/conf.py
doc/development.rst
doc/index.rst
doc/make.bat
doc/usage.rst
stereovision/__init__.py
stereovision/blockmatchers.py
stereovision/calibration.py
stereovision/exceptions.py
stereovision/point_cloud.py
stereovision/stereo_cameras.py
stereovision/ui_utils.py