Metadata-Version: 1.1
Name: StereoVision
Version: 1.0.2
Summary: Library and utilities for 3d reconstruction from stereo cameras.
Home-page: http://erget.github.com/StereoVision
Author: Daniel Lee
Author-email: lee.daniel.1986@gmail.com
License: GNU GPL
Download-URL: http://pypi.python.org/pypi/StereoVision
Platform: UNKNOWN
Classifier: Development Status :: 5 - Production/Stable
Classifier: Natural Language :: English
Classifier: Operating System :: OS Independent
Classifier: Programming Language :: Python :: 2
Classifier: Intended Audience :: Developers
Classifier: Intended Audience :: Education
Classifier: Intended Audience :: Science/Research
Classifier: License :: Freely Distributable
Classifier: License :: OSI Approved :: GNU General Public License v3 or later (GPLv3+)
Classifier: Natural Language :: English
Classifier: Operating System :: OS Independent
Classifier: Programming Language :: Python :: 2.7
Classifier: Topic :: Multimedia :: Graphics :: Capture
Requires: cv2
Requires: simplejson
Requires: numpy
Requires: progressbar
Provides: stereovision
